硬件描述语言原理与应用/方法探索_32位除法器/Divider.v
`timescale 1ns / 10ps

module Divider (
    input             clk        ,
    input             rst        , 
    input      [31:0] dividend   , 
    input      [31:0] divisor    , 
    output reg [31:0] remainder  , 
    output reg [31:0] quotient     
);
    //state number
    parameter WAIT = 0, GMSB = 1, NEXT = 2, SHIFT = 3, CHECK_DONE = 4;

    reg [63:0] temp_remainder    ;
    reg [63:0] new_divisor       ;
    reg [31:0] temp_a, temp_b    ;

    //L1 saves the MSB of dividend, L2 saves the MSB of divisor
    //L1,L2,f range from -31 to 31, the highest bit is the sign bit
    reg [5 :0] f, L1, L2         ; 
    reg [3 :0] state, next_state ;

    //initial 
    always @(rst) begin
        temp_a    = dividend ;
        temp_b    = divisor  ;
        L1        = 0        ;
        L2        = 0        ;
    end

    //三段式FSM
    always @(posedge clk) begin
        if (rst) 
            state <= WAIT;
        else
            state <= next_state;
    end

    always @(state) begin
        case(state)
            WAIT:
                next_state = (divisor == 0)? CHECK_DONE : GMSB;
            GMSB:
                next_state = NEXT;
            NEXT:        
                next_state = (f[5] != 0)? CHECK_DONE : SHIFT;
            SHIFT:
                next_state = CHECK_DONE;  
            CHECK_DONE:
                next_state = (f[5] != 0)? CHECK_DONE : SHIFT;
            default: ;
        endcase
    end

    always @(posedge clk) begin
        case(state)
            WAIT: begin // 0 initial
                remainder   <= dividend              ;
                quotient    <= 0                     ;
                new_divisor <= {divisor, {32{1'b0}}} ;
            end
            GMSB: begin // 1 get the MSB and subtract
                //可综合 用if
                if     (temp_a[31] == 1) L1 = 31;
                else if(temp_a[30] == 1) L1 = 30;
                else if(temp_a[29] == 1) L1 = 29;
                else if(temp_a[28] == 1) L1 = 28;
                else if(temp_a[27] == 1) L1 = 27;
                else if(temp_a[26] == 1) L1 = 26;
                else if(temp_a[25] == 1) L1 = 25;
                else if(temp_a[24] == 1) L1 = 24;
                else if(temp_a[23] == 1) L1 = 23;
                else if(temp_a[22] == 1) L1 = 22;
                else if(temp_a[21] == 1) L1 = 21;
                else if(temp_a[20] == 1) L1 = 20;
                else if(temp_a[19] == 1) L1 = 19;
                else if(temp_a[18] == 1) L1 = 18;
                else if(temp_a[17] == 1) L1 = 17;
                else if(temp_a[16] == 1) L1 = 16;
                else if(temp_a[15] == 1) L1 = 15;
                else if(temp_a[14] == 1) L1 = 14;
                else if(temp_a[13] == 1) L1 = 13;
                else if(temp_a[12] == 1) L1 = 12;
                else if(temp_a[11] == 1) L1 = 11;
                else if(temp_a[10] == 1) L1 = 10;
                else if(temp_a[9 ] == 1) L1 = 9 ;
                else if(temp_a[8 ] == 1) L1 = 8 ;
                else if(temp_a[7 ] == 1) L1 = 7 ;
                else if(temp_a[6 ] == 1) L1 = 6 ;
                else if(temp_a[5 ] == 1) L1 = 5 ;
                else if(temp_a[4 ] == 1) L1 = 4 ;
                else if(temp_a[3 ] == 1) L1 = 3 ;
                else if(temp_a[2 ] == 1) L1 = 2 ;
                else if(temp_a[1 ] == 1) L1 = 1 ;
                else                     L1 = 0 ;

                if     (temp_b[31] == 1) L2 = 31;
                else if(temp_b[30] == 1) L2 = 30;
                else if(temp_b[29] == 1) L2 = 29;
                else if(temp_b[28] == 1) L2 = 28;
                else if(temp_b[27] == 1) L2 = 27;
                else if(temp_b[26] == 1) L2 = 26;
                else if(temp_b[25] == 1) L2 = 25;
                else if(temp_b[24] == 1) L2 = 24;
                else if(temp_b[23] == 1) L2 = 23;
                else if(temp_b[22] == 1) L2 = 22;
                else if(temp_b[21] == 1) L2 = 21;
                else if(temp_b[20] == 1) L2 = 20;
                else if(temp_b[19] == 1) L2 = 19;
                else if(temp_b[18] == 1) L2 = 18;
                else if(temp_b[17] == 1) L2 = 17;
                else if(temp_b[16] == 1) L2 = 16;
                else if(temp_b[15] == 1) L2 = 15;
                else if(temp_b[14] == 1) L2 = 14;
                else if(temp_b[13] == 1) L2 = 13;
                else if(temp_b[12] == 1) L2 = 12;
                else if(temp_b[11] == 1) L2 = 11;
                else if(temp_b[10] == 1) L2 = 10;
                else if(temp_b[9 ] == 1) L2 = 9 ;
                else if(temp_b[8 ] == 1) L2 = 8 ;
                else if(temp_b[7 ] == 1) L2 = 7 ;
                else if(temp_b[6 ] == 1) L2 = 6 ;
                else if(temp_b[5 ] == 1) L2 = 5 ;
                else if(temp_b[4 ] == 1) L2 = 4 ;
                else if(temp_b[3 ] == 1) L2 = 3 ;
                else if(temp_b[2 ] == 1) L2 = 2 ;
                else if(temp_b[1 ] == 1) L2 = 1 ;
                else                     L2 = 0 ;

                // f = L1 - L2;
                f = L1 + (~L2 + 1);
            end
            NEXT: begin // 2
                temp_remainder   <= {dividend, {32{1'b0}}} ;
                quotient         <= 0                      ;
                case(f)
                    0 : new_divisor <= {new_divisor[63:0], { 0{1'b0}}};
                    1 : new_divisor <= {new_divisor[62:0], { 1{1'b0}}};
                    2 : new_divisor <= {new_divisor[61:0], { 2{1'b0}}};
                    3 : new_divisor <= {new_divisor[60:0], { 3{1'b0}}};
                    4 : new_divisor <= {new_divisor[59:0], { 4{1'b0}}};
                    5 : new_divisor <= {new_divisor[58:0], { 5{1'b0}}};
                    6 : new_divisor <= {new_divisor[57:0], { 6{1'b0}}};
                    7 : new_divisor <= {new_divisor[56:0], { 7{1'b0}}};
                    8 : new_divisor <= {new_divisor[55:0], { 8{1'b0}}};
                    9 : new_divisor <= {new_divisor[54:0], { 9{1'b0}}};
                    10: new_divisor <= {new_divisor[53:0], {10{1'b0}}};
                    11: new_divisor <= {new_divisor[52:0], {11{1'b0}}};
                    12: new_divisor <= {new_divisor[51:0], {12{1'b0}}};
                    13: new_divisor <= {new_divisor[50:0], {13{1'b0}}};
                    14: new_divisor <= {new_divisor[49:0], {14{1'b0}}};
                    15: new_divisor <= {new_divisor[48:0], {15{1'b0}}};
                    16: new_divisor <= {new_divisor[47:0], {16{1'b0}}};
                    17: new_divisor <= {new_divisor[46:0], {17{1'b0}}};
                    18: new_divisor <= {new_divisor[45:0], {18{1'b0}}};
                    19: new_divisor <= {new_divisor[44:0], {19{1'b0}}};
                    20: new_divisor <= {new_divisor[43:0], {20{1'b0}}};
                    21: new_divisor <= {new_divisor[42:0], {21{1'b0}}};
                    22: new_divisor <= {new_divisor[41:0], {22{1'b0}}};
                    23: new_divisor <= {new_divisor[40:0], {23{1'b0}}};
                    24: new_divisor <= {new_divisor[39:0], {24{1'b0}}};
                    25: new_divisor <= {new_divisor[38:0], {25{1'b0}}};
                    26: new_divisor <= {new_divisor[37:0], {26{1'b0}}};
                    27: new_divisor <= {new_divisor[36:0], {27{1'b0}}};
                    28: new_divisor <= {new_divisor[35:0], {28{1'b0}}};
                    29: new_divisor <= {new_divisor[34:0], {29{1'b0}}};
                    30: new_divisor <= {new_divisor[33:0], {30{1'b0}}};
                    31: new_divisor <= {new_divisor[32:0], {31{1'b0}}};
                    default: ;
                endcase
                
            end
            SHIFT: begin // 3
                if(temp_remainder >= new_divisor) begin
                    quotient       <= {quotient[30:0], 1'b1}       ;
                    temp_remainder <= temp_remainder - new_divisor ;
                    new_divisor    <= {1'b0, new_divisor[62:1]}    ;
                end
                else begin
                    quotient       <= {quotient[30:0], 1'b0}    ;
                    temp_remainder <= temp_remainder            ;
                    new_divisor    <= {1'b0, new_divisor[62:1]} ;
                end   
                f = f + 6'b111111;             
            end
            CHECK_DONE: begin // 4
                //if divisor is zero ,set quotient to max value, set remainder to dividend
                if(divisor == 0) begin
                    remainder <= dividend   ;
                    quotient  <= {32{1'b1}} ;
                end
                else begin
                    remainder <= temp_remainder[63:32] ;
                end;
            end
            default: ;
        endcase
    end

endmodule

硬件描述语言原理与应用/方法探索_32位除法器/Divider_tb.v
`timescale 1ns / 10ps

module Divider_tb;
    //inputs
    reg        clk       ;
    reg        rst       ;
    reg [31:0] dividend  ;
    reg [31:0] divisor   ;

    //outputs
    reg [31:0] remainder ;
    reg [31:0] quotient  ;

    parameter delay = 10 ;

    Divider 
        U_Divider(
            .clk(clk)            ,
            .rst(rst)            ,
            .dividend(dividend)  ,
            .divisor(divisor)    ,
            .remainder(remainder),
            .quotient(quotient)
        );

    initial begin
        //create .vpd file
        `ifdef DUMP_VPD
               $vcdpluson();
        `endif
        //create .vcd file
        $dumpfile("divider_wave.vcd");
        $dumpvars;
    end

    //clock
	always #(delay/2) clk=~clk;

    initial begin
        // initial 
        clk       = 0  ; 
        rst       = 1  ;
        
        //normal case 1
        dividend  = 74 ; //32'b0000_0000_0000_0000_0000_0000_0100_1010;
        divisor   = 8  ; //32'b0000_0000_0000_0000_0000_0000_0000_1000;
        #(delay * 1.5 + 1) rst = 0;

        //divided
        #(delay * 15     ) rst = 1; 
                           dividend = 32'b1111_0000_0000_0000_0000_0000_0000_0000 ; 
                           divisor  = 32'b0000_0000_0000_0000_0000_0000_0000_1111 ;
        #(delay * 1.5 + 1) rst = 0;

        //divisor > dividend
        #(delay * 65     ) rst = 1; dividend = 65  ; divisor = 109;
        #(delay * 1.5 + 1) rst = 0;

        //divisor is zero
        #(delay * 15     ) rst = 1; dividend = 86  ; divisor = 0  ;
        #(delay * 1.5 + 1) rst = 0;

        #(delay * 15     ) $finish;
    end

endmodule

硬件描述语言原理与应用/方法探索_32位除法器/divider_wave.vcd
$date
	Sun Oct 30 15:06:47 2022
$end

$version
	Synopsys VCS version G-2012.09
$end

$timescale
	10ps
$end

$comment Csum: 1 8ccc54f5867f973e $end


$scope module Divider_tb $end
$var reg 1 ! clk $end
$var reg 1 " rst $end
$var reg 32 # dividend [31:0] $end
$var reg 32 $ divisor [31:0] $end
$var reg 32 % remainder [31:0] $end
$var reg 32 & quotient [31:0] $end

$scope module U_Divider $end
$var wire 1 ! clk $end
$var wire 1 " rst $end
$var wire 32 # dividend [31:0] $end
$var wire 32 $ divisor [31:0] $end
$var reg 32 ' remainder [31:0] $end
$var reg 32 ( quotient [31:0] $end
$var reg 64 ) temp_remainder [63:0] $end
$var reg 64 * new_divisor [63:0] $end
$var reg 32 + temp_a [31:0] $end
$var reg 32 , temp_b [31:0] $end
$var reg 6 - f [5:0] $end
$var reg 6 . L1 [5:0] $end
$var reg 6 / L2 [5:0] $end
$var reg 4 0 state [3:0] $end
$var reg 4 1 next_state [3:0] $end
$upscope $end

$upscope $end

$enddefinitions $end

#0
$dumpvars
0!
1"
b000000 .
b000000 /
bxxxxxxxxxxxxxxxxxxxxxxxxxxxxxxxx (
bxxxxxxxxxxxxxxxxxxxxxxxxxxxxxxxx '
b00000000000000000000000001001010 #
b00000000000000000000000000001000 $
bxxxxxx -
bxxxxxxxxxxxxxxxxxxxxxxxxxxxxxxxxxxxxxxxxxxxxxxxxxxxxxxxxxxxxxxxx *
bxxxx 1
bxxxxxxxxxxxxxxxxxxxxxxxxxxxxxxxx &
bxxxxxxxxxxxxxxxxxxxxxxxxxxxxxxxx %
bxxxx 0
b00000000000000000000000001001010 +
b00000000000000000000000000001000 ,
bxxxxxxxxxxxxxxxxxxxxxxxxxxxxxxxxxxxxxxxxxxxxxxxxxxxxxxxxxxxxxxxx )
$end
#500
1!
b0000 0
b0001 1
#1000
0!
#1500
1!
b00000000000000000000000001001010 '
b00000000000000000000000001001010 %
b00000000000000000000000000000000 (
b00000000000000000000000000000000 &
b0000000000000000000000000000100000000000000000000000000000000000 *
#1600
0"
#2000
0!
#2500
1!
b0001 0
b0010 1
#3000
0!
#3500
1!
b000110 .
b000011 /
b000011 -
b0010 0
b0011 1
#4000
0!
#4500
1!
b0011 0
b0000000000000000000000000100101000000000000000000000000000000000 )
b0000000000000000000000000100000000000000000000000000000000000000 *
b0100 1
#5000
0!
#5500
1!
b000010 -
b0100 0
b00000000000000000000000000000001 (
b00000000000000000000000000000001 &
b0000000000000000000000000000101000000000000000000000000000000000 )
b0000000000000000000000000010000000000000000000000000000000000000 *
b0011 1
#6000
0!
#6500
1!
b0011 0
b00000000000000000000000000001010 '
b00000000000000000000000000001010 %
b0100 1
#7000
0!
#7500
1!
b000001 -
b0100 0
b00000000000000000000000000000010 (
b00000000000000000000000000000010 &
b0000000000000000000000000001000000000000000000000000000000000000 *
b0011 1
#8000
0!
#8500
1!
b0011 0
b0100 1
#9000
0!
#9500
1!
b000000 -
b0100 0
b00000000000000000000000000000100 (
b00000000000000000000000000000100 &
b0000000000000000000000000000100000000000000000000000000000000000 *
b0011 1
#10000
0!
#10500
1!
b0011 0
b0100 1
#11000
0!
#11500
1!
b111111 -
b0100 0
b00000000000000000000000000001001 (
b00000000000000000000000000001001 &
b0000000000000000000000000000001000000000000000000000000000000000 )
b0000000000000000000000000000010000000000000000000000000000000000 *
#12000
0!
#12500
1!
b00000000000000000000000000000010 '
b00000000000000000000000000000010 %
#13000
0!
#13500
1!
#14000
0!
#14500
1!
#15000
0!
#15500
1!
#16000
0!
#16500
1!
#16600
1"
b11110000000000000000000000000000 #
b00000000000000000000000000001111 $
b11110000000000000000000000000000 +
b00000000000000000000000000001111 ,
b000000 .
b000000 /
#17000
0!
#17500
1!
b0000 0
b0001 1
#18000
0!
#18200
0"
#18500
1!
b0001 0
b11110000000000000000000000000000 '
b11110000000000000000000000000000 %
b00000000000000000000000000000000 (
b00000000000000000000000000000000 &
b0000000000000000000000000000111100000000000000000000000000000000 *
b0010 1
#19000
0!
#19500
1!
b011111 .
b000011 /
b011100 -
b0010 0
b0011 1
#20000
0!
#20500
1!
b0011 0
b1111000000000000000000000000000000000000000000000000000000000000 )
b1111000000000000000000000000000000000000000000000000000000000000 *
b0100 1
#21000
0!
#21500
1!
b011011 -
b0100 0
b00000000000000000000000000000001 (
b00000000000000000000000000000001 &
b0000000000000000000000000000000000000000000000000000000000000000 )
b0011100000000000000000000000000000000000000000000000000000000000 *
b0011 1
#22000
0!
#22500
1!
b0011 0
b00000000000000000000000000000000 '
b00000000000000000000000000000000 %
b0100 1
#23000
0!
#23500
1!
b011010 -
b0100 0
b00000000000000000000000000000010 (
b00000000000000000000000000000010 &
b0001110000000000000000000000000000000000000000000000000000000000 *
b0011 1
#24000
0!
#24500
1!
b0011 0
b0100 1
#25000
0!
#25500
1!
b011001 -
b0100 0
b00000000000000000000000000000100 (
b00000000000000000000000000000100 &
b0000111000000000000000000000000000000000000000000000000000000000 *
b0011 1
#26000
0!
#26500
1!
b0011 0
b0100 1
#27000
0!
#27500
1!
b011000 -
b0100 0
b00000000000000000000000000001000 (
b00000000000000000000000000001000 &
b0000011100000000000000000000000000000000000000000000000000000000 *
b0011 1
#28000
0!
#28500
1!
b0011 0
b0100 1
#29000
0!
#29500
1!
b010111 -
b0100 0
b00000000000000000000000000010000 (
b00000000000000000000000000010000 &
b0000001110000000000000000000000000000000000000000000000000000000 *
b0011 1
#30000
0!
#30500
1!
b0011 0
b0100 1
#31000
0!
#31500
1!
b010110 -
b0100 0
b00000000000000000000000000100000 (
b00000000000000000000000000100000 &
b0000000111000000000000000000000000000000000000000000000000000000 *
b0011 1
#32000
0!
#32500
1!
b0011 0
b0100 1
#33000
0!
#33500
1!
b010101 -
b0100 0
b00000000000000000000000001000000 (
b00000000000000000000000001000000 &
b0000000011100000000000000000000000000000000000000000000000000000 *
b0011 1
#34000
0!
#34500
1!
b0011 0
b0100 1
#35000
0!
#35500
1!
b010100 -
b0100 0
b00000000000000000000000010000000 (
b00000000000000000000000010000000 &
b0000000001110000000000000000000000000000000000000000000000000000 *
b0011 1
#36000
0!
#36500
1!
b0011 0
b0100 1
#37000
0!
#37500
1!
b010011 -
b0100 0
b00000000000000000000000100000000 (
b00000000000000000000000100000000 &
b0000000000111000000000000000000000000000000000000000000000000000 *
b0011 1
#38000
0!
#38500
1!
b0011 0
b0100 1
#39000
0!
#39500
1!
b010010 -
b0100 0
b00000000000000000000001000000000 (
b00000000000000000000001000000000 &
b0000000000011100000000000000000000000000000000000000000000000000 *
b0011 1
#40000
0!
#40500
1!
b0011 0
b0100 1
#41000
0!
#41500
1!
b010001 -
b0100 0
b00000000000000000000010000000000 (
b00000000000000000000010000000000 &
b0000000000001110000000000000000000000000000000000000000000000000 *
b0011 1
#42000
0!
#42500
1!
b0011 0
b0100 1
#43000
0!
#43500
1!
b010000 -
b0100 0
b00000000000000000000100000000000 (
b00000000000000000000100000000000 &
b0000000000000111000000000000000000000000000000000000000000000000 *
b0011 1
#44000
0!
#44500
1!
b0011 0
b0100 1
#45000
0!
#45500
1!
b001111 -
b0100 0
b00000000000000000001000000000000 (
b00000000000000000001000000000000 &
b0000000000000011100000000000000000000000000000000000000000000000 *
b0011 1
#46000
0!
#46500
1!
b0011 0
b0100 1
#47000
0!
#47500
1!
b001110 -
b0100 0
b00000000000000000010000000000000 (
b00000000000000000010000000000000 &
b0000000000000001110000000000000000000000000000000000000000000000 *
b0011 1
#48000
0!
#48500
1!
b0011 0
b0100 1
#49000
0!
#49500
1!
b001101 -
b0100 0
b00000000000000000100000000000000 (
b00000000000000000100000000000000 &
b0000000000000000111000000000000000000000000000000000000000000000 *
b0011 1
#50000
0!
#50500
1!
b0011 0
b0100 1
#51000
0!
#51500
1!
b001100 -
b0100 0
b00000000000000001000000000000000 (
b00000000000000001000000000000000 &
b0000000000000000011100000000000000000000000000000000000000000000 *
b0011 1
#52000
0!
#52500
1!
b0011 0
b0100 1
#53000
0!
#53500
1!
b001011 -
b0100 0
b00000000000000010000000000000000 (
b00000000000000010000000000000000 &
b0000000000000000001110000000000000000000000000000000000000000000 *
b0011 1
#54000
0!
#54500
1!
b0011 0
b0100 1
#55000
0!
#55500
1!
b001010 -
b0100 0
b00000000000000100000000000000000 (
b00000000000000100000000000000000 &
b0000000000000000000111000000000000000000000000000000000000000000 *
b0011 1
#56000
0!
#56500
1!
b0011 0
b0100 1
#57000
0!
#57500
1!
b001001 -
b0100 0
b00000000000001000000000000000000 (
b00000000000001000000000000000000 &
b0000000000000000000011100000000000000000000000000000000000000000 *
b0011 1
#58000
0!
#58500
1!
b0011 0
b0100 1
#59000
0!
#59500
1!
b001000 -
b0100 0
b00000000000010000000000000000000 (
b00000000000010000000000000000000 &
b0000000000000000000001110000000000000000000000000000000000000000 *
b0011 1
#60000
0!
#60500
1!
b0011 0
b0100 1
#61000
0!
#61500
1!
b000111 -
b0100 0
b00000000000100000000000000000000 (
b00000000000100000000000000000000 &
b0000000000000000000000111000000000000000000000000000000000000000 *
b0011 1
#62000
0!
#62500
1!
b0011 0
b0100 1
#63000
0!
#63500
1!
b000110 -
b0100 0
b00000000001000000000000000000000 (
b00000000001000000000000000000000 &
b0000000000000000000000011100000000000000000000000000000000000000 *
b0011 1
#64000
0!
#64500
1!
b0011 0
b0100 1
#65000
0!
#65500
1!
b000101 -
b0100 0
b00000000010000000000000000000000 (
b00000000010000000000000000000000 &
b0000000000000000000000001110000000000000000000000000000000000000 *
b0011 1
#66000
0!
#66500
1!
b0011 0
b0100 1
#67000
0!
#67500
1!
b000100 -
b0100 0
b00000000100000000000000000000000 (
b00000000100000000000000000000000 &
b0000000000000000000000000111000000000000000000000000000000000000 *
b0011 1
#68000
0!
#68500
1!
b0011 0
b0100 1
#69000
0!
#69500
1!
b000011 -
b0100 0
b00000001000000000000000000000000 (
b00000001000000000000000000000000 &
b0000000000000000000000000011100000000000000000000000000000000000 *
b0011 1
#70000
0!
#70500
1!
b0011 0
b0100 1
#71000
0!
#71500
1!
b000010 -
b0100 0
b00000010000000000000000000000000 (
b00000010000000000000000000000000 &
b0000000000000000000000000001110000000000000000000000000000000000 *
b0011 1
#72000
0!
#72500
1!
b0011 0
b0100 1
#73000
0!
#73500
1!
b000001 -
b0100 0
b00000100000000000000000000000000 (
b00000100000000000000000000000000 &
b0000000000000000000000000000111000000000000000000000000000000000 *
b0011 1
#74000
0!
#74500
1!
b0011 0
b0100 1
#75000
0!
#75500
1!
b000000 -
b0100 0
b00001000000000000000000000000000 (
b00001000000000000000000000000000 &
b0000000000000000000000000000011100000000000000000000000000000000 *
b0011 1
#76000
0!
#76500
1!
b0011 0
b0100 1
#77000
0!
#77500
1!
b111111 -
b0100 0
b00010000000000000000000000000000 (
b00010000000000000000000000000000 &
b0000000000000000000000000000001110000000000000000000000000000000 *
#78000
0!
#78500
1!
#79000
0!
#79500
1!
#80000
0!
#80500
1!
#81000
0!
#81500
1!
#82000
0!
#82500
1!
#83000
0!
#83200
1"
b00000000000000000000000001000001 #
b00000000000000000000000001101101 $
b00000000000000000000000001000001 +
b00000000000000000000000001101101 ,
b000000 .
b000000 /
#83500
1!
b0000 0
b0001 1
#84000
0!
#84500
1!
b00000000000000000000000001000001 '
b00000000000000000000000001000001 %
b00000000000000000000000000000000 (
b00000000000000000000000000000000 &
b0000000000000000000000000110110100000000000000000000000000000000 *
#84800
0"
#85000
0!
#85500
1!
b0001 0
b0010 1
#86000
0!
#86500
1!
b000110 .
b000110 /
b000000 -
b0010 0
b0011 1
#87000
0!
#87500
1!
b0011 0
b0000000000000000000000000100000100000000000000000000000000000000 )
b0100 1
#88000
0!
#88500
1!
b111111 -
b0100 0
b0000000000000000000000000011011010000000000000000000000000000000 *
#89000
0!
#89500
1!
#90000
0!
#90500
1!
#91000
0!
#91500
1!
#92000
0!
#92500
1!
#93000
0!
#93500
1!
#94000
0!
#94500
1!
#95000
0!
#95500
1!
#96000
0!
#96500
1!
#97000
0!
#97500
1!
#98000
0!
#98500
1!
#99000
0!
#99500
1!
#99800
1"
b00000000000000000000000001010110 #
b00000000000000000000000000000000 $
b00000000000000000000000001010110 +
b00000000000000000000000000000000 ,
b000000 .
b000000 /
#100000
0!
#100500
1!
b0000 0
b00000000000000000000000001010110 '
b00000000000000000000000001010110 %
b11111111111111111111111111111111 (
b11111111111111111111111111111111 &
#101000
0!
#101400
0"
#101500
1!
b0100 0
b00000000000000000000000000000000 (
b00000000000000000000000000000000 &
b0000000000000000000000000000000000000000000000000000000000000000 *
#102000
0!
#102500
1!
b11111111111111111111111111111111 (
b11111111111111111111111111111111 &
