硬件描述语言原理与应用/课程设计_浮点单元设计/FPU.v
`timescale 1ns / 10ps

module FPU(
    input             clk        ,
    input             rst        , 
    input      [31:0] dividend   , 
    input      [31:0] divisor    , 
    output reg [31:0] quotient     
);
    //define state numbers
    parameter RESET = 0, WAIT = 1, NEXT = 2, SHIFT = 3, CHECK = 4, ROUND = 5, DONE = 6;

    reg [47:0] new_divisor       ;
    reg [47:0] remainder         ;
    reg [24:0] temp_quotient     ;
    reg [8 :0] quotient_exponent ; // 9bits, since (exponent-127) ranges from  -127 to 380
    reg [7 :0] temp_exponent     ;   
    reg [4 :0] flag              ; 
    reg [2 :0] state             ;
    reg [2 :0] next_state        ;
    reg [3 :0] special = 0       ; // special cases (NaN,infinity or zero)

    //Three-Stage FSM
    always @(posedge clk) begin
        if (rst) 
            state <= RESET;
        else
            state <= next_state;
    end

    always @(state) begin
        case(state)
            RESET:
                next_state = WAIT;
            WAIT:
                next_state = NEXT;
            NEXT:
                next_state = SHIFT;
            SHIFT:
                if(special == 0)        // normal case
                    next_state = CHECK;
                else if(special == 10)  // downflow
                    next_state = NEXT;
                else                    // special cases expect downflow
                    next_state = DONE;        
            CHECK:
                next_state = (flag == 0)? ROUND : SHIFT;
            ROUND:
                next_state = DONE;
            DONE:
                next_state = DONE;
            default: ;
        endcase
    end

    always @(posedge clk) begin
        case(state)
            RESET: begin
                // initial
                special           <= 0 ;
                quotient          <= 0 ;
                remainder         <= 0 ;
                new_divisor       <= 0 ;
                quotient_exponent <= 0 ;
            end
            WAIT: begin
                // special cases (NaN,infinity or zero)
                if((dividend[30:23] != 8'b1111_1111 && dividend[30:0] != 0) && (divisor[30:23] == 8'b1111_1111 && divisor[22:0] == 0)) begin 
                    // special case 1 : x / infinity = 0 (x not NaN,infinity or zero)
                    special <= 1 ;
                end
                else if((dividend[30:23] != 8'b1111_1111 && dividend[30:0] != 0) && (divisor[30:0] == 0)) begin 
                    // special case 2 : x / 0 = infinity (x not NaN,infinity or zero)
                    special <= 2 ;
                end
                else if((dividend[30:0] == 0) && (divisor[30:0] == 0)) begin 
                    // special case 3 : 0 / 0 = NaN
                    special <= 3 ;
                end
                else if((dividend[30:23] == 8'b1111_1111 && dividend[22:0] == 0) && (divisor[30:23] == 8'b1111_1111 && divisor[22:0] == 0)) begin
                    // special case 4 : infinity / infinity = NaN
                    special <= 4 ;
                end 
                else if((dividend[30:23] == 8'b1111_1111 && dividend[22:0] != 0) || (divisor[30:23] == 8'b1111_1111 && divisor[22:0] != 0)) begin
                    // special case 5 : dividend or divisor is NaN, quotient is NaN
                    special <= 5 ;
                end
                else if((dividend[30:23] == 8'b1111_1111 && dividend[22:0] == 0) && (divisor[30:0] == 0)) begin
                    // special case 6 : infinity / 0 = infinity
                    special <= 6 ;
                end
                else if((dividend[30:23] == 8'b1111_1111 && dividend[22:0] == 0) && (divisor[30:23] != 8'b1111_1111 && divisor[30:0] != 0)) begin
                    // special case 7 : infinity / x = infinity (x not NaN,infinity or zero)
                    special <= 7 ;
                end
                else if((dividend[30:0] == 0) && (divisor[30:23] != 8'b1111_1111 && divisor[30:0] != 0)) begin
                    // special case 8 : zero / x = zero (x not NaN,infinity or zero)
                    special <= 8 ;
                end
                else begin
                    // special case 0 : normal case , special case 9 : overflow and special case 10 : downflow
                    remainder     <= (dividend[30:23] == 0)? {1'b0, dividend[22:0], {24{1'b0}}} : {1'b1, dividend[22:0], {24{1'b0}}} ; //add 0 when unnormalized
                    temp_quotient <= 0 ;
                    if(dividend[22:0] >= divisor[22:0]) begin
                        // dividend's mantissa >= divisor's mantissa
                        quotient_exponent <= dividend[30:23] - divisor[30:23] + 127 ;
                        new_divisor       <= (divisor[30:23] == 0)? {1'b0, divisor[22:0], {24{1'b0}}} : {1'b1, divisor[22:0], {24{1'b0}}} ; //add 0 when unnormalized
                        temp_exponent     <= dividend[30:23] ;
                    end 
                    else begin
                        // dividend's mantissa < divisor's mantissa 
                        // when divisor is unnormalized, it should be specially considered  
                        quotient_exponent <= (divisor[30:23] == 0)? (dividend[30:23] - divisor[30:23] + 127) : (dividend[30:23] - divisor[30:23] + 126) ;
                        new_divisor       <= (divisor[30:23] == 0)? {divisor[22:0], {25{1'b0}}} : {2'b01, divisor[22:0], {23{1'b0}}} ;
                        temp_exponent     <= dividend[30:23] - 1 ; 
                    end
                end
            end
            NEXT: begin
                // determine the number of SHIFT
                // when the quotient of two normalized floating point number is unnormalized, it should be specially considered
                flag <= (quotient_exponent == 0 && dividend[30:23] != 0 && divisor[30:23] != 0)? 23 : 24 ;

                // check overflow or downflow
                if((dividend[22:0] >= divisor[22:0] && dividend[30:23] + 127 >= divisor[30:23] && special == 0) 
                || (dividend[22:0] <  divisor[22:0] && dividend[30:23] + 126 >= divisor[30:23] && special == 0)
                ) begin
                    // check overflow
                    // special case 9 : overflow, quotient is infinity
                    special <= (quotient_exponent > 254)? 9 : 0 ;
                end
                else if(special == 0 || special == 10) begin
                    // downflow
                    // special case 10 : downflow, quotient will shift right until the exponent is -126
                    special           <= (temp_exponent - divisor[30:23] + 126 == 0)? 0 : 10 ;
                    quotient_exponent <= 0                       ;
                    remainder         <= {1'b0, remainder[47:1]} ;
                end
                else ;
            end
            SHIFT: begin
                if(special != 10) begin
                    if(remainder >= new_divisor) begin
                        temp_quotient <= {temp_quotient[23:0], 1'b1} ;
                        remainder     <= remainder - new_divisor     ;
                        new_divisor   <= {1'b0, new_divisor[47:1]}   ;
                    end
                    else begin
                        temp_quotient <= {temp_quotient[23:0], 1'b0} ;
                        remainder     <= remainder                   ;
                        new_divisor   <= {1'b0, new_divisor[47:1]}   ;
                    end   
                    flag <= flag - 1;         
                end
                else begin
                    temp_exponent <= temp_exponent + 1 ; 
                end
            end
            CHECK: begin
                if(flag == 0) begin //Rounding mode
                    if((remainder == new_divisor && temp_quotient[0] == 1'b0) || (remainder < new_divisor)) begin
                        ; 
                    end
                    else begin
                        temp_quotient <= temp_quotient + 1 ;
                    end
                end
                else ;
            end
            ROUND: begin
                if(temp_quotient[24] == 1) begin
                    quotient_exponent <= quotient_exponent + 1       ;
                    temp_quotient     <= {1'b0, temp_quotient[23:0]} ;
                end
                else ;
            end
            DONE: begin
                quotient[31] <= dividend[31] ^ divisor[31] ; // determine the sign bit
                case(special)
                    0: begin
                        // normal case
                        quotient[30:23] <= quotient_exponent[7:0] ;
                        quotient[22: 0] <= (quotient_exponent[7:0] == 8'b1111_1111)? 0 : temp_quotient[22:0] ; // if exponent overflow, quotient = infinity
                    end
                    1: begin
                        //  x / infinity = 0 (x not NaN,infinity or zero)
                        quotient[30:23] <= 0 ;
                        quotient[22: 0] <= 0 ;
                    end
                    2: begin
                        //  x / 0 = infinity (x not NaN,infinity or zero)
                        quotient[30:23] <= 8'b1111_1111 ;
                        quotient[22: 0] <= 0            ;
                    end
                    3: begin
                        //  0 / 0 = NaN
                        quotient[30:23] <= 8'b1111_1111 ;
                        quotient[22: 0] <= {23{1'b1}}   ;
                    end
                    4: begin
                        //  infinity / infinity = NaN
                        quotient[30:23] <= 8'b1111_1111 ;
                        quotient[22: 0] <= {23{1'b1}}   ;
                    end
                    5: begin
                        //  dividend or divisor is NaN, quotient is NaN
                        quotient[30:23] <= 8'b1111_1111 ;
                        quotient[22: 0] <= {23{1'b1}}   ;
                    end
                    6: begin
                        //  infinity / 0 = infinity
                        quotient[30:23] <= 8'b1111_1111 ;
                        quotient[22: 0] <= 0            ;
                    end
                    7: begin
                        //  infinity / x = infinity (x not NaN,infinity or zero)
                        quotient[30:23] <= 8'b1111_1111 ;
                        quotient[22: 0] <= 0            ;
                    end
                    8: begin
                        //  zero / x = zero (x not NaN,infinity or zero)
                        quotient[30:23] <= 0            ;
                        quotient[22: 0] <= 0            ;
                    end
                    9: begin
                        // overflow, output should be infinity
                        quotient[30:23] <= 8'b1111_1111 ;
                        quotient[22: 0] <= 0            ;
                    end
                    default: ;
                endcase
            end
            default: ;
        endcase        
        
    end

endmodule

硬件描述语言原理与应用/课程设计_浮点单元设计/FPU_tb.v
`timescale 1ns / 10ps

module FPU_tb;
    //inputs
    reg        clk      ;
    reg        rst      ;
    reg [31:0] dividend ;
    reg [31:0] divisor  ;

    //outputs
    reg [31:0] quotient ;

    parameter delay = 5 ;

    FPU 
        U_FPU(
            .clk(clk)           ,
            .rst(rst)           ,
            .dividend(dividend) ,
            .divisor(divisor)   ,
            .quotient(quotient)
        );

    initial begin
        //create .vpd file
        `ifdef DUMP_VPD
            $vcdpluson();
        `endif
        //create .vcd file
        $dumpfile("FPU_Wave.vcd");
        $dumpvars;
    end

    //clock
	always #(delay/2) clk=~clk;

    initial begin
        // initial 
        clk       = 0  ; 
        rst       = 1  ;

        // special == 0 : 1.5 / 0.5 = 3
        // output should be 0_10000000_10000000000000000000000
        dividend = 32'b0_01111111_10000000000000000000000; //1.5
        divisor  = 32'b0_01111110_00000000000000000000000; //0.5
        #(delay * 1.5 + 1) rst = 0;

        // special == 0 : 0.5 / 1.5 = 0.33333333
        // output should be 0_01111101_01010101010101010101011
        #(delay * 45     ) rst = 1;
                           dividend = 32'b0_01111110_00000000000000000000000; //0.5
                           divisor  = 32'b0_01111111_10000000000000000000000; //1.5
        #(delay * 1.5 + 1) rst = 0;
        
        // special == 0 : dividend is unnormalized
        // output should be 0_00000000_01100010101010101010101
        #(delay * 45     ) rst = 1;
                           dividend = 32'b0_00000000_10010100000000000000000; //unnormalized
                           divisor  = 32'b0_01111111_10000000000000000000000; 
        #(delay * 1.5 + 1) rst = 0;

        // special == 0 : divisor is unnormalized
        // output should be 0_11111110_00011101110001000111100
        #(delay * 45     ) rst = 1;
                           dividend = 32'b0_01111111_10000000000000000000000; 
                           divisor  = 32'b0_00000000_10101100000000000000000; //unnormalized
        #(delay * 1.5 + 1) rst = 0;

        // special == 0 : dividend and divisor are both unnormalized
        // output should be 0_01111111_01011000000000000000000
        #(delay * 45     ) rst = 1;
                           dividend = 32'b0_00000000_10101100000000000000000; //unnormalized
                           divisor  = 32'b0_00000000_10000000000000000000000; //unnormalized
        #(delay * 1.5 + 1) rst = 0;

        // special == 0 : quotient is unnormalized
        // output should be 0_00000000_10100000011110100100010
        #(delay * 45     ) rst = 1;
                           dividend = 32'b0_01000000_11111000000000000000000; 
                           divisor  = 32'b0_10111111_10010010000000000000000;
        #(delay * 1.5 + 1) rst = 0;

        // special == 1 : x / infinity = 0 (x not NaN,infinity or zero)
        // output should be zero
        #(delay * 45     ) rst = 1;
                           dividend = 32'b0_01111111_10000000000000000000000; //1.5
                           divisor  = 32'b0_11111111_00000000000000000000000; //infinity
        #(delay * 1.5 + 1) rst = 0;

        // special == 2 : x / 0 = infinity (x not NaN,infinity or zero)
        // output should be infinity
        #(delay * 45     ) rst = 1;
                           dividend = 32'b0_01111111_10000000000000000000000; //1.5
                           divisor  = 32'b0_00000000_00000000000000000000000; //zero
        #(delay * 1.5 + 1) rst = 0;

        // special == 3 : 0 / 0 = NaN
        // output should be NaN
        #(delay * 45     ) rst = 1;
                           dividend = 32'b0_00000000_00000000000000000000000; //zero
                           divisor  = 32'b0_00000000_00000000000000000000000; //zero
        #(delay * 1.5 + 1) rst = 0;

        // special == 4 : infinity / infinity = NaN
        // output should be NaN
        #(delay * 45     ) rst = 1;
                           dividend = 32'b0_11111111_00000000000000000000000; //infinity
                           divisor  = 32'b0_11111111_00000000000000000000000; //infinity
        #(delay * 1.5 + 1) rst = 0;

        // special == 5 : dividend is NaN, quotient is NaN
        // output should be NaN
        #(delay * 45     ) rst = 1;
                           dividend = 32'b0_11111111_11110000000000000000000; //NaN
                           divisor  = 32'b0_00000000_00000000000000000000000; //zero
        #(delay * 1.5 + 1) rst = 0;

        // special == 5 : divisor is NaN, quotient is NaN
        // output should be NaN
        #(delay * 45     ) rst = 1;
                           dividend = 32'b0_01111111_10000000000000000000000; //1.5
                           divisor  = 32'b0_11111111_11110000000000000000000; //NaN
        #(delay * 1.5 + 1) rst = 0;

        // special == 5 : dividend and divisor are both NaN, quotient is NaN
        // output should be NaN
        #(delay * 45     ) rst = 1;
                           dividend = 32'b0_11111111_11110000000000000000000; //NaN
                           divisor  = 32'b0_11111111_11110000000000000000000; //NaN
        #(delay * 1.5 + 1) rst = 0;

        // special == 6 : infinity / 0 = infinity
        // output should be infinity
        #(delay * 45     ) rst = 1;
                           dividend = 32'b0_11111111_00000000000000000000000; //infinity
                           divisor  = 32'b0_00000000_00000000000000000000000; //zero
        #(delay * 1.5 + 1) rst = 0;

        // special == 7 : infinity / x = infinity (x not NaN,infinity or zero)
        // output should be infinity
        #(delay * 45     ) rst = 1;
                           dividend = 32'b0_11111111_00000000000000000000000; //infinity
                           divisor  = 32'b0_01111111_10000000000000000000000; 
        #(delay * 1.5 + 1) rst = 0;

        // special == 8 : zero / x = zero (x not NaN,infinity or zero)
        // output should be zero
        #(delay * 45     ) rst = 1;
                           dividend = 32'b0_00000000_00000000000000000000000; //zero
                           divisor  = 32'b0_01111111_10000000000000000000000; 
        #(delay * 1.5 + 1) rst = 0;

        // special == 9 : overflow, quotient is infinity
        // output should be infinity
        #(delay * 45     ) rst = 1;
                           dividend = 32'b0_10000011_01000000000000000000000; 
                           divisor  = 32'b0_00000011_01000000000000000000000;
        #(delay * 1.5 + 1) rst = 0;

        // special == 10 : quotient is zero
        // output should be zero
        #(delay * 45     ) rst = 1;
                           dividend = 32'b0_00000011_01000000000000000000000; 
                           divisor  = 32'b0_10011111_01000000000000000000000;
        #(delay * 1.5 + 1) rst = 0;

        #(delay * 100    ) $finish;

    end

endmodule

硬件描述语言原理与应用/课程设计_浮点单元设计/FPU_Wave.vcd
$date
	Wed Oct 26 13:43:18 2022
$end

$version
	Synopsys VCS version G-2012.09
$end

$timescale
	10ps
$end

$comment Csum: 1 015681a6c6ca33b8 $end


$scope module FPU_tb $end
$var reg 1 ! clk $end
$var reg 1 " rst $end
$var reg 32 # dividend [31:0] $end
$var reg 32 $ divisor [31:0] $end
$var reg 32 % quotient [31:0] $end

$scope module U_FPU $end
$var wire 1 ! clk $end
$var wire 1 " rst $end
$var wire 32 # dividend [31:0] $end
$var wire 32 $ divisor [31:0] $end
$var reg 32 & quotient [31:0] $end
$var reg 48 ' new_divisor [47:0] $end
$var reg 48 ( remainder [47:0] $end
$var reg 25 ) temp_quotient [24:0] $end
$var reg 9 * quotient_exponent [8:0] $end
$var reg 8 + temp_exponent [7:0] $end
$var reg 5 , flag [4:0] $end
$var reg 3 - state [2:0] $end
$var reg 3 . next_state [2:0] $end
$var reg 4 / special [3:0] $end
$upscope $end

$upscope $end

$enddefinitions $end

#0
$dumpvars
0!
1"
bxxxxxxxxxxxxxxxxxxxxxxxxxxxxxxxx &
b00111111110000000000000000000000 #
b00111111000000000000000000000000 $
bxxxxx ,
bxxxxxxxxxxxxxxxxxxxxxxxxxxxxxxxxxxxxxxxxxxxxxxxx '
bxxx .
bxxxxxxxxxxxxxxxxxxxxxxxxxxxxxxxx %
bxxxxxxxxx *
bxxxxxxxxxxxxxxxxxxxxxxxxxxxxxxxxxxxxxxxxxxxxxxxx (
b0000 /
bxxx -
bxxxxxxxx +
bxxxxxxxxxxxxxxxxxxxxxxxxx )
$end
#200
1!
b000 -
b001 .
#400
0!
#600
1!
b00000000000000000000000000000000 &
b00000000000000000000000000000000 %
b000000000000000000000000000000000000000000000000 (
b000000000000000000000000000000000000000000000000 '
b000000000 *
#800
0!
#850
0"
#1000
1!
b001 -
b010 .
#1200
0!
#1400
1!
b010 -
b110000000000000000000000000000000000000000000000 (
b0000000000000000000000000 )
b010000000 *
b100000000000000000000000000000000000000000000000 '
b01111111 +
b011 .
#1600
0!
#1800
1!
b011 -
b11000 ,
b100 .
#2000
0!
#2200
1!
b100 -
b0000000000000000000000001 )
b010000000000000000000000000000000000000000000000 (
b010000000000000000000000000000000000000000000000 '
b10111 ,
b011 .
#2400
0!
#2600
1!
b011 -
b100 .
#2800
0!
#3000
1!
b100 -
b0000000000000000000000011 )
b000000000000000000000000000000000000000000000000 (
b001000000000000000000000000000000000000000000000 '
b10110 ,
b011 .
#3200
0!
#3400
1!
b011 -
b100 .
#3600
0!
#3800
1!
b100 -
b0000000000000000000000110 )
b000100000000000000000000000000000000000000000000 '
b10101 ,
b011 .
#4000
0!
#4200
1!
b011 -
b100 .
#4400
0!
#4600
1!
b100 -
b0000000000000000000001100 )
b000010000000000000000000000000000000000000000000 '
b10100 ,
b011 .
#4800
0!
#5000
1!
b011 -
b100 .
#5200
0!
#5400
1!
b100 -
b0000000000000000000011000 )
b000001000000000000000000000000000000000000000000 '
b10011 ,
b011 .
#5600
0!
#5800
1!
b011 -
b100 .
#6000
0!
#6200
1!
b100 -
b0000000000000000000110000 )
b000000100000000000000000000000000000000000000000 '
b10010 ,
b011 .
#6400
0!
#6600
1!
b011 -
b100 .
#6800
0!
#7000
1!
b100 -
b0000000000000000001100000 )
b000000010000000000000000000000000000000000000000 '
b10001 ,
b011 .
#7200
0!
#7400
1!
b011 -
b100 .
#7600
0!
#7800
1!
b100 -
b0000000000000000011000000 )
b000000001000000000000000000000000000000000000000 '
b10000 ,
b011 .
#8000
0!
#8200
1!
b011 -
b100 .
#8400
0!
#8600
1!
b100 -
b0000000000000000110000000 )
b000000000100000000000000000000000000000000000000 '
b01111 ,
b011 .
#8800
0!
#9000
1!
b011 -
b100 .
#9200
0!
#9400
1!
b100 -
b0000000000000001100000000 )
b000000000010000000000000000000000000000000000000 '
b01110 ,
b011 .
#9600
0!
#9800
1!
b011 -
b100 .
#10000
0!
#10200
1!
b100 -
b0000000000000011000000000 )
b000000000001000000000000000000000000000000000000 '
b01101 ,
b011 .
#10400
0!
#10600
1!
b011 -
b100 .
#10800
0!
#11000
1!
b100 -
b0000000000000110000000000 )
b000000000000100000000000000000000000000000000000 '
b01100 ,
b011 .
#11200
0!
#11400
1!
b011 -
b100 .
#11600
0!
#11800
1!
b100 -
b0000000000001100000000000 )
b000000000000010000000000000000000000000000000000 '
b01011 ,
b011 .
#12000
0!
#12200
1!
b011 -
b100 .
#12400
0!
#12600
1!
b100 -
b0000000000011000000000000 )
b000000000000001000000000000000000000000000000000 '
b01010 ,
b011 .
#12800
0!
#13000
1!
b011 -
b100 .
#13200
0!
#13400
1!
b100 -
b0000000000110000000000000 )
b000000000000000100000000000000000000000000000000 '
b01001 ,
b011 .
#13600
0!
#13800
1!
b011 -
b100 .
#14000
0!
#14200
1!
b100 -
b0000000001100000000000000 )
b000000000000000010000000000000000000000000000000 '
b01000 ,
b011 .
#14400
0!
#14600
1!
b011 -
b100 .
#14800
0!
#15000
1!
b100 -
b0000000011000000000000000 )
b000000000000000001000000000000000000000000000000 '
b00111 ,
b011 .
#15200
0!
#15400
1!
b011 -
b100 .
#15600
0!
#15800
1!
b100 -
b0000000110000000000000000 )
b000000000000000000100000000000000000000000000000 '
b00110 ,
b011 .
#16000
0!
#16200
1!
b011 -
b100 .
#16400
0!
#16600
1!
b100 -
b0000001100000000000000000 )
b000000000000000000010000000000000000000000000000 '
b00101 ,
b011 .
#16800
0!
#17000
1!
b011 -
b100 .
#17200
0!
#17400
1!
b100 -
b0000011000000000000000000 )
b000000000000000000001000000000000000000000000000 '
b00100 ,
b011 .
#17600
0!
#17800
1!
b011 -
b100 .
#18000
0!
#18200
1!
b100 -
b0000110000000000000000000 )
b000000000000000000000100000000000000000000000000 '
b00011 ,
b011 .
#18400
0!
#18600
1!
b011 -
b100 .
#18800
0!
#19000
1!
b100 -
b0001100000000000000000000 )
b000000000000000000000010000000000000000000000000 '
b00010 ,
b011 .
#19200
0!
#19400
1!
b011 -
b100 .
#19600
0!
#19800
1!
b100 -
b0011000000000000000000000 )
b000000000000000000000001000000000000000000000000 '
b00001 ,
b011 .
#20000
0!
#20200
1!
b011 -
b100 .
#20400
0!
#20600
1!
b100 -
b0110000000000000000000000 )
b000000000000000000000000100000000000000000000000 '
b00000 ,
b101 .
#20800
0!
#21000
1!
b101 -
b110 .
#21200
0!
#21400
1!
b110 -
#21600
0!
#21800
1!
b01000000000000000000000000000000 &
b01000000000000000000000000000000 %
b01000000010000000000000000000000 &
b01000000010000000000000000000000 %
#22000
0!
#22200
1!
#22400
0!
#22600
1!
#22800
0!
#23000
1!
#23200
0!
#23350
1"
b00111111000000000000000000000000 #
b00111111110000000000000000000000 $
#23400
1!
b000 -
b001 .
#23600
0!
#23800
1!
b00000000000000000000000000000000 &
b00000000000000000000000000000000 %
b000000000000000000000000000000000000000000000000 '
b000000000 *
#24000
0!
#24200
0"
1!
b001 -
b010 .
#24400
0!
#24600
1!
b010 -
b100000000000000000000000000000000000000000000000 (
b0000000000000000000000000 )
b001111101 *
b011000000000000000000000000000000000000000000000 '
b01111101 +
b011 .
#24800
0!
#25000
1!
b011 -
b11000 ,
b100 .
#25200
0!
#25400
1!
b100 -
b0000000000000000000000001 )
b001000000000000000000000000000000000000000000000 (
b001100000000000000000000000000000000000000000000 '
b10111 ,
b011 .
#25600
0!
#25800
1!
b011 -
b100 .
#26000
0!
#26200
1!
b100 -
b0000000000000000000000010 )
b000110000000000000000000000000000000000000000000 '
b10110 ,
b011 .
#26400
0!
#26600
1!
b011 -
b100 .
#26800
0!
#27000
1!
b100 -
b0000000000000000000000101 )
b000010000000000000000000000000000000000000000000 (
b000011000000000000000000000000000000000000000000 '
b10101 ,
b011 .
#27200
0!
#27400
1!
b011 -
b100 .
#27600
0!
#27800
1!
b100 -
b0000000000000000000001010 )
b000001100000000000000000000000000000000000000000 '
b10100 ,
b011 .
#28000
0!
#28200
1!
b011 -
b100 .
#28400
0!
#28600
1!
b100 -
b0000000000000000000010101 )
b000000100000000000000000000000000000000000000000 (
b000000110000000000000000000000000000000000000000 '
b10011 ,
b011 .
#28800
0!
#29000
1!
b011 -
b100 .
#29200
0!
#29400
1!
b100 -
b0000000000000000000101010 )
b000000011000000000000000000000000000000000000000 '
b10010 ,
b011 .
#29600
0!
#29800
1!
b011 -
b100 .
#30000
0!
#30200
1!
b100 -
b0000000000000000001010101 )
b000000001000000000000000000000000000000000000000 (
b000000001100000000000000000000000000000000000000 '
b10001 ,
b011 .
#30400
0!
#30600
1!
b011 -
b100 .
#30800
0!
#31000
1!
b100 -
b0000000000000000010101010 )
b000000000110000000000000000000000000000000000000 '
b10000 ,
b011 .
#31200
0!
#31400
1!
b011 -
b100 .
#31600
0!
#31800
1!
b100 -
b0000000000000000101010101 )
b000000000010000000000000000000000000000000000000 (
b000000000011000000000000000000000000000000000000 '
b01111 ,
b011 .
#32000
0!
#32200
1!
b011 -
b100 .
#32400
0!
#32600
1!
b100 -
b0000000000000001010101010 )
b000000000001100000000000000000000000000000000000 '
b01110 ,
b011 .
#32800
0!
#33000
1!
b011 -
b100 .
#33200
0!
#33400
1!
b100 -
b0000000000000010101010101 )
b000000000000100000000000000000000000000000000000 (
b000000000000110000000000000000000000000000000000 '
b01101 ,
b011 .
#33600
0!
#33800
1!
b011 -
b100 .
#34000
0!
#34200
1!
b100 -
b0000000000000101010101010 )
b000000000000011000000000000000000000000000000000 '
b01100 ,
b011 .
#34400
0!
#34600
1!
b011 -
b100 .
#34800
0!
#35000
1!
b100 -
b0000000000001010101010101 )
b000000000000001000000000000000000000000000000000 (
b000000000000001100000000000000000000000000000000 '
b01011 ,
b011 .
#35200
0!
#35400
1!
b011 -
b100 .
#35600
0!
#35800
1!
b100 -
b0000000000010101010101010 )
b000000000000000110000000000000000000000000000000 '
b01010 ,
b011 .
#36000
0!
#36200
1!
b011 -
b100 .
#36400
0!
#36600
1!
b100 -
b0000000000101010101010101 )
b000000000000000010000000000000000000000000000000 (
b000000000000000011000000000000000000000000000000 '
b01001 ,
b011 .
#36800
0!
#37000
1!
b011 -
b100 .
#37200
0!
#37400
1!
b100 -
b0000000001010101010101010 )
b000000000000000001100000000000000000000000000000 '
b01000 ,
b011 .
#37600
0!
#37800
1!
b011 -
b100 .
#38000
0!
#38200
1!
b100 -
b0000000010101010101010101 )
b000000000000000000100000000000000000000000000000 (
b000000000000000000110000000000000000000000000000 '
b00111 ,
b011 .
#38400
0!
#38600
1!
b011 -
b100 .
#38800
0!
#39000
1!
b100 -
b0000000101010101010101010 )
b000000000000000000011000000000000000000000000000 '
b00110 ,
b011 .
#39200
0!
#39400
1!
b011 -
b100 .
#39600
0!
#39800
1!
b100 -
b0000001010101010101010101 )
b000000000000000000001000000000000000000000000000 (
b000000000000000000001100000000000000000000000000 '
b00101 ,
b011 .
#40000
0!
#40200
1!
b011 -
b100 .
#40400
0!
#40600
1!
b100 -
b0000010101010101010101010 )
b000000000000000000000110000000000000000000000000 '
b00100 ,
b011 .
#40800
0!
#41000
1!
b011 -
b100 .
#41200
0!
#41400
1!
b100 -
b0000101010101010101010101 )
b000000000000000000000010000000000000000000000000 (
b000000000000000000000011000000000000000000000000 '
b00011 ,
b011 .
#41600
0!
#41800
1!
b011 -
b100 .
#42000
0!
#42200
1!
b100 -
b0001010101010101010101010 )
b000000000000000000000001100000000000000000000000 '
b00010 ,
b011 .
#42400
0!
#42600
1!
b011 -
b100 .
#42800
0!
#43000
1!
b100 -
b0010101010101010101010101 )
b000000000000000000000000100000000000000000000000 (
b000000000000000000000000110000000000000000000000 '
b00001 ,
b011 .
#43200
0!
#43400
1!
b011 -
b100 .
#43600
0!
#43800
1!
b100 -
b0101010101010101010101010 )
b000000000000000000000000011000000000000000000000 '
b00000 ,
b101 .
#44000
0!
#44200
1!
b101 -
b0101010101010101010101011 )
b110 .
#44400
0!
#44600
1!
b110 -
#44800
0!
#45000
1!
b00111110100000000000000000000000 &
b00111110100000000000000000000000 %
b00111110101010101010101010101011 &
b00111110101010101010101010101011 %
#45200
0!
#45400
1!
#45600
0!
#45800
1!
#46000
0!
#46200
1!
#46400
0!
#46600
1!
#46700
1"
b00000000010010100000000000000000 #
#46800
0!
#47000
1!
b000 -
b001 .
#47200
0!
#47400
1!
b00000000000000000000000000000000 &
b00000000000000000000000000000000 %
b000000000000000000000000000000000000000000000000 (
b000000000000000000000000000000000000000000000000 '
b000000000 *
#47550
0"
#47600
0!
#47800
1!
b001 -
b010 .
#48000
0!
#48200
1!
b010 -
b010010100000000000000000000000000000000000000000 (
b0000000000000000000000000 )
b110000000000000000000000000000000000000000000000 '
b00000000 +
b011 .
#48400
0!
#48600
1!
b011 -
b11000 ,
b100 .
#48800
0!
#49000
1!
b100 -
b011000000000000000000000000000000000000000000000 '
b10111 ,
b011 .
#49200
0!
#49400
1!
b011 -
b100 .
#49600
0!
#49800
1!
b100 -
b001100000000000000000000000000000000000000000000 '
b10110 ,
b011 .
#50000
0!
#50200
1!
b011 -
b100 .
#50400
0!
#50600
1!
b100 -
b0000000000000000000000001 )
b000110100000000000000000000000000000000000000000 (
b000110000000000000000000000000000000000000000000 '
b10101 ,
b011 .
#50800
0!
#51000
1!
b011 -
b100 .
#51200
0!
#51400
1!
b100 -
b0000000000000000000000011 )
b000000100000000000000000000000000000000000000000 (
b000011000000000000000000000000000000000000000000 '
b10100 ,
b011 .
#51600
0!
#51800
1!
b011 -
b100 .
#52000
0!
#52200
1!
b100 -
b0000000000000000000000110 )
b000001100000000000000000000000000000000000000000 '
b10011 ,
b011 .
#52400
0!
#52600
1!
b011 -
b100 .
#52800
0!
#53000
1!
b100 -
b0000000000000000000001100 )
b000000110000000000000000000000000000000000000000 '
b10010 ,
b011 .
#53200
0!
#53400
1!
b011 -
b100 .
#53600
0!
#53800
1!
b100 -
b0000000000000000000011000 )
b000000011000000000000000000000000000000000000000 '
b10001 ,
b011 .
#54000
0!
#54200
1!
b011 -
b100 .
#54400
0!
#54600
1!
b100 -
b0000000000000000000110001 )
b000000001000000000000000000000000000000000000000 (
b000000001100000000000000000000000000000000000000 '
b10000 ,
b011 .
#54800
0!
#55000
1!
b011 -
b100 .
#55200
0!
#55400
1!
b100 -
b0000000000000000001100010 )
b000000000110000000000000000000000000000000000000 '
b01111 ,
b011 .
#55600
0!
#55800
1!
b011 -
b100 .
#56000
0!
#56200
1!
b100 -
b0000000000000000011000101 )
b000000000010000000000000000000000000000000000000 (
b000000000011000000000000000000000000000000000000 '
b01110 ,
b011 .
#56400
0!
#56600
1!
b011 -
b100 .
#56800
0!
#57000
1!
b100 -
b0000000000000000110001010 )
b000000000001100000000000000000000000000000000000 '
b01101 ,
b011 .
#57200
0!
#57400
1!
b011 -
b100 .
#57600
0!
#57800
1!
b100 -
b0000000000000001100010101 )
b000000000000100000000000000000000000000000000000 (
b000000000000110000000000000000000000000000000000 '
b01100 ,
b011 .
#58000
0!
#58200
1!
b011 -
b100 .
#58400
0!
#58600
1!
b100 -
b0000000000000011000101010 )
b000000000000011000000000000000000000000000000000 '
b01011 ,
b011 .
#58800
0!
#59000
1!
b011 -
b100 .
#59200
0!
#59400
1!
b100 -
b0000000000000110001010101 )
b000000000000001000000000000000000000000000000000 (
b000000000000001100000000000000000000000000000000 '
b01010 ,
b011 .
#59600
0!
#59800
1!
b011 -
b100 .
#60000
0!
#60200
1!
b100 -
b0000000000001100010101010 )
b000000000000000110000000000000000000000000000000 '
b01001 ,
b011 .
#60400
0!
#60600
1!
b011 -
b100 .
#60800
0!
#61000
1!
b100 -
b0000000000011000101010101 )
b000000000000000010000000000000000000000000000000 (
b000000000000000011000000000000000000000000000000 '
b01000 ,
b011 .
#61200
0!
#61400
1!
b011 -
b100 .
#61600
0!
#61800
1!
b100 -
b0000000000110001010101010 )
b000000000000000001100000000000000000000000000000 '
b00111 ,
b011 .
#62000
0!
#62200
1!
b011 -
b100 .
#62400
0!
#62600
1!
b100 -
b0000000001100010101010101 )
b000000000000000000100000000000000000000000000000 (
b000000000000000000110000000000000000000000000000 '
b00110 ,
b011 .
#62800
0!
